pymatchseries/__init__.py
pymatchseries/config_tools.py
pymatchseries/default_parameters.param
pymatchseries/io_utils.py
pymatchseries/matchseries.py
pyMatchSeries-0.1.0.dist-info/LICENSE
pyMatchSeries-0.1.0.dist-info/METADATA
pyMatchSeries-0.1.0.dist-info/WHEEL
pyMatchSeries-0.1.0.dist-info/top_level.txt
pyMatchSeries-0.1.0.dist-info/RECORD
