Metadata-Version: 2.1
Name: pyMatchSeries
Version: 0.1.0
Summary: A python wrapper for the non-rigid-registration code match-series
Home-page: https://github.com/din14970/pyMatchSeries
Author: Niels Cautaerts
Author-email: nielscautaerts@hotmail.com
License: GPL-3.0
Keywords: TEM
Platform: UNKNOWN
Classifier: Topic :: Scientific/Engineering :: Physics
Classifier: Intended Audience :: Science/Research
Classifier: Operating System :: OS Independent
Classifier: Programming Language :: Python :: 3.7
Classifier: Programming Language :: Python :: 3.8
Requires-Dist: hyperspy (>=1.6.1)
Requires-Dist: Pillow
Requires-Dist: tabulate
Provides-Extra: dev
Requires-Dist: black (>=19.3b0) ; extra == 'dev'
Requires-Dist: pre-commit (>=1.16) ; extra == 'dev'
Requires-Dist: sphinx (>=3.0.2) ; extra == 'dev'
Requires-Dist: sphinx-rtd-theme (>=0.4.3) ; extra == 'dev'
Requires-Dist: pytest (>=5.4) ; extra == 'dev'
Requires-Dist: pytest-cov (>=2.8.1) ; extra == 'dev'
Requires-Dist: coverage (>=5.0) ; extra == 'dev'
Provides-Extra: doc
Requires-Dist: sphinx (>=3.0.2) ; extra == 'doc'
Requires-Dist: sphinx-rtd-theme (>=0.4.3) ; extra == 'doc'
Provides-Extra: tests
Requires-Dist: pytest (>=5.4) ; extra == 'tests'
Requires-Dist: pytest-cov (>=2.8.1) ; extra == 'tests'
Requires-Dist: coverage (>=5.0) ; extra == 'tests'
